LICENSE
README.md
pyproject.toml
setup.cfg
setup.py
pygeonlp_webapi/__init__.py
pygeonlp_webapi/app.py
pygeonlp_webapi.egg-info/PKG-INFO
pygeonlp_webapi.egg-info/SOURCES.txt
pygeonlp_webapi.egg-info/dependency_links.txt
pygeonlp_webapi.egg-info/requires.txt
pygeonlp_webapi.egg-info/top_level.txt
pygeonlp_webapi/config/default.py