Metadata-Version: 2.1
Name: pygeonlp-webapi
Version: 1.1.0
Summary: Pygeonlp WebAPI Server
Home-page: https://github.com/geonlp-platform/pygeonlp_webapi
Author: GeoNLP Project Team
Author-email: geonlp@nii.ac.jp
License: BSD-2-Clause
Download-URL: https://github.com/geonlp-platform/pygeonlp_webapi
Keywords: geonlp,webapi,server,json-rpc
Platform: UNKNOWN
Classifier: Programming Language :: Python :: 3
Classifier: Programming Language :: Python :: 3.6
Classifier: Programming Language :: Python :: 3.7
Classifier: Programming Language :: Python :: 3.8
Classifier: Programming Language :: Python :: 3.9
License-File: LICENSE
